Metadata-Version: 1.0
Name: cgcloud-lib
Version: 1.6.0
Summary: Components shared between cgcloud-core and cgcloud-agent
Home-page: https://github.com/BD2KGenomics/cgcloud
Author: Hannes Schmidt
Author-email: hannes@ucsc.edu
License: UNKNOWN
Platform: UNKNOWN
